fastg2protlib/__init__.py
fastg2protlib/db.py
fastg2protlib/fastg2protlib.py
fastg2protlib/mzid_sax_parsing.py
fastg2protlib/protein_score.py
fastg2protlib-0.1.8.dist-info/LICENSE.txt
fastg2protlib-0.1.8.dist-info/METADATA
fastg2protlib-0.1.8.dist-info/WHEEL
fastg2protlib-0.1.8.dist-info/top_level.txt
fastg2protlib-0.1.8.dist-info/RECORD
