Metadata-Version: 2.1
Name: fastg2protlib
Version: 0.1.8
Summary: FASTG sequences to a protein library
Home-page: https://github.umn.edu/mcgo0092/fastg2protlib.git
Author: Thomas McGowan
Author-email: mcgo0092@umn.edu
License: MIT
Download-URL: https://github.umn.edu/mcgo0092/fastg2protlib/archive/v_0.1.8.tar.gz
Platform: UNKNOWN
Classifier: Development Status :: 3 - Alpha
Classifier: Programming Language :: Python :: 3
Classifier: License :: OSI Approved :: MIT License
Classifier: Operating System :: OS Independent
Requires-Python: >=3.6
Requires-Dist: biopython
Requires-Dist: lxml
Requires-Dist: networkx
Requires-Dist: numpy
Requires-Dist: pyteomics
